openai_hacker/__init__.py
openai_hacker/_hack.py
openai_hacker/conf.py
openai_hacker-0.1.3.dist-info/LICENSE
openai_hacker-0.1.3.dist-info/METADATA
openai_hacker-0.1.3.dist-info/WHEEL
openai_hacker-0.1.3.dist-info/top_level.txt
openai_hacker-0.1.3.dist-info/RECORD
